api/__init__.py
api/arxiv.py
api/dictionary.py
api/openlibrary.py
api/wikipedia.py
models/__init__.py
models/article.py
models/base.py
models/book.py
models/definition.py
models/research_paper.py
mseep_openedu_mcp_server-1.0.1.dist-info/licenses/LICENSE
services/__init__.py
services/cache_service.py
services/rate_limiting_service.py
services/usage_service.py
tools/__init__.py
tools/arxiv_tools.py
tools/base_tool.py
tools/dictionary_tools.py
tools/openlibrary_tools.py
tools/wikipedia_tools.py
utils/__init__.py
utils/validation.py
mseep_openedu_mcp_server-1.0.1.dist-info/METADATA
mseep_openedu_mcp_server-1.0.1.dist-info/WHEEL
mseep_openedu_mcp_server-1.0.1.dist-info/entry_points.txt
mseep_openedu_mcp_server-1.0.1.dist-info/top_level.txt
mseep_openedu_mcp_server-1.0.1.dist-info/RECORD
