Metadata-Version: 2.4
Name: mseep-openedu-mcp-server
Version: 1.0.1
Summary: OpenEdu MCP Server for educational resources and curriculum planning
Author-email: mseep <support@skydeck.ai>
License: MIT
Classifier: Development Status :: 4 - Beta
Classifier: Intended Audience :: Education
Classifier: License :: OSI Approved :: MIT License
Classifier: Programming Language :: Python :: 3
Classifier: Programming Language :: Python :: 3.9
Classifier: Programming Language :: Python :: 3.10
Classifier: Programming Language :: Python :: 3.11
Classifier: Programming Language :: Python :: 3.12
Requires-Python: >=3.9
License-File: LICENSE
Requires-Dist: fastmcp>=0.1.0
Requires-Dist: uvicorn>=0.24.0
Requires-Dist: httpx>=0.25.0
Requires-Dist: aiosqlite>=0.19.0
Requires-Dist: pydantic>=2.5.0
Requires-Dist: pyyaml>=6.0.1
Requires-Dist: python-dotenv>=1.0.0
Requires-Dist: structlog>=23.2.0
Provides-Extra: dev
Requires-Dist: pytest>=7.4.0; extra == "dev"
Requires-Dist: pytest-asyncio>=0.21.0; extra == "dev"
Requires-Dist: pytest-cov>=4.1.0; extra == "dev"
Requires-Dist: black>=23.0.0; extra == "dev"
Requires-Dist: isort>=5.12.0; extra == "dev"
Requires-Dist: mypy>=1.7.0; extra == "dev"
Dynamic: license-file
